LICENSE
perm_banana/Check.py
perm_banana/CheckStrategy/Strategy.py
perm_banana/CheckStrategy/StrategyCheck.py
perm_banana/CheckStrategy/StrategyHandler.py
perm_banana/CheckStrategy/StrategyPermission.py
perm_banana/CheckStrategy/StrategyPermissions.py
perm_banana/CheckStrategy/__init__.py
perm_banana/MetaCheck.py
perm_banana/NameConflictException.py
perm_banana/Permission.py
perm_banana/PermissionHandler.py
perm_banana/__init__.py
perm_banana/banana.py
perm_banana-0.2.1.dist-info/LICENSE
perm_banana-0.2.1.dist-info/WHEEL
perm_banana-0.2.1.dist-info/METADATA
perm_banana-0.2.1.dist-info/RECORD
