Metadata-Version: 2.1
Name: perm-banana
Version: 0.2.1
Summary: A Bitwise Permission Handler
Home-page: https://github.com/TheJoeSmo/perm-banana
License: MIT
Keywords: permissions,bitwise
Author: TheJoeSmo
Author-email: joesmo.joesmo12@gmail.com
Requires-Python: >=3.7,<4.0
Classifier: License :: OSI Approved :: MIT License
Classifier: Programming Language :: Python :: 3
Classifier: Programming Language :: Python :: 3.7
Classifier: Programming Language :: Python :: 3.8
Classifier: Programming Language :: Python :: 3.9
Project-URL: Repository, https://github.com/TheJoeSmo/perm-banana
